block_timer/__init__.py
block_timer/timer.py
block_timer-0.2.0.dist-info/METADATA
block_timer-0.2.0.dist-info/RECORD
block_timer-0.2.0.dist-info/WHEEL
block_timer-0.2.0.dist-info/top_level.txt
block_timer-0.2.0.dist-info/zip-safe
