Metadata-Version: 2.1
Name: block-timer
Version: 0.2.0
Summary: Measure execution time of your code blocks
Home-page: https://github.com/illagrenan/block-timer
Author: Vasek Dohnal
Author-email: vaclav.dohnal@gmail.com
License: MIT
Platform: UNKNOWN
Classifier: Development Status :: 3 - Alpha
Classifier: Intended Audience :: Developers
Classifier: License :: OSI Approved :: MIT License
Classifier: Natural Language :: English
Classifier: Programming Language :: Python :: 3.4
Classifier: Programming Language :: Python :: 3.5
Classifier: Programming Language :: Python :: 3.6
Classifier: Programming Language :: Python :: 3.7
Classifier: Programming Language :: Python :: 3 :: Only
Classifier: Operating System :: OS Independent
Requires-Python: ~=3.4
Requires-Dist: typing; python_version<'3.5'
